fixie/__init__.py
fixie/client.py
fixie/client_test.py
fixie/main.py
fixie_sdk-0.1.0.dist-info/LICENSE
fixie_sdk-0.1.0.dist-info/WHEEL
fixie_sdk-0.1.0.dist-info/METADATA
fixie_sdk-0.1.0.dist-info/RECORD
